[
    {
        "strikePrice": 5300,
        "expiryDate": "29-Feb-2024",
        "CE": {
            "strikePrice": 5300,
            "expiryDate": "29-Feb-2024",
            "underlying": "APOLLOHOSP",
            "identifier": "OPTSTKAPOLLOHOSP29-02-2024CE5300.00",
            "openInterest": 0,
            "changeinOpenInterest": 0,
            "pchangeinOpenInterest": 0,
            "totalTradedVolume": 0,
            "impliedVolatility": 0,
            "lastPrice": 0,
            "change": 0,
            "pChange": 0,
            "totalBuyQuantity": 6250,
            "totalSellQuantity": 1500,
            "bidQty": 375,
            "bidprice": 560.05,
            "askQty": 250,
            "askPrice": 683.35,
            "underlyingValue": 5807.45
        },
        "PE": {
            "strikePrice": 5300,
            "expiryDate": "29-Feb-2024",
            "underlying": "APOLLOHOSP",
            "identifier": "OPTSTKAPOLLOHOSP29-02-2024PE5300.00",
            "openInterest": 2,
            "changeinOpenInterest": 0,
            "pchangeinOpenInterest": 0,
            "totalTradedVolume": 0,
            "impliedVolatility": 0,
            "lastPrice": 50,
            "change": 0,
            "pChange": 0,
            "totalBuyQuantity": 1750,
            "totalSellQuantity": 125,
            "bidQty": 125,
            "bidprice": 25.85,
            "askQty": 125,
            "askPrice": 50,
            "underlyingValue": 5807.45
        }
    },
    {
        "strikePrice": 5350,
        "expiryDate": "29-Feb-2024",
        "PE": {
            "strikePrice": 5350,
            "expiryDate": "29-Feb-2024",
            "underlying": "APOLLOHOSP",
            "identifier": "OPTSTKAPOLLOHOSP29-02-2024PE5350.00",
            "openInterest": 0,
            "changeinOpenInterest": 0,
            "pchangeinOpenInterest": 0,
            "totalTradedVolume": 0,
            "impliedVolatility": 0,
            "lastPrice": 0,
            "change": 0,
            "pChange": 0,
            "totalBuyQuantity": 1625,
            "totalSellQuantity": 0,
            "bidQty": 1500,
            "bidprice": 5.55,
            "askQty": 0,
            "askPrice": 0,
            "underlyingValue": 5807.45
        },
        "CE": {
            "strikePrice": 5350,
            "expiryDate": "29-Feb-2024",
            "underlying": "APOLLOHOSP",
            "identifier": "OPTSTKAPOLLOHOSP29-02-2024CE5350.00",
            "openInterest": 0,
            "changeinOpenInterest": 0,
            "pchangeinOpenInterest": 0,
            "totalTradedVolume": 0,
            "impliedVolatility": 0,
            "lastPrice": 0,
            "change": 0,
            "pChange": 0,
            "totalBuyQuantity": 6250,
            "totalSellQuantity": 1250,
            "bidQty": 375,
            "bidprice": 486.3,
            "askQty": 375,
            "askPrice": 773.6,
            "underlyingValue": 5807.45
        }
    },
    {
        "strikePrice": 5400,
        "expiryDate": "29-Feb-2024",
        "PE": {
            "strikePrice": 5400,
            "expiryDate": "29-Feb-2024",
            "underlying": "APOLLOHOSP",
            "identifier": "OPTSTKAPOLLOHOSP29-02-2024PE5400.00",
            "openInterest": 1,
            "changeinOpenInterest": 1,
            "pchangeinOpenInterest": 0,
            "totalTradedVolume": 1,
            "impliedVolatility": 26.64,
            "lastPrice": 55,
            "change": -184.25,
            "pChange": -77.01149425287356,
            "totalBuyQuantity": 1750,
            "totalSellQuantity": 125,
            "bidQty": 125,
            "bidprice": 39.8,
            "askQty": 125,
            "askPrice": 88,
            "underlyingValue": 5807.45
        },
        "CE": {
            "strikePrice": 5400,
            "expiryDate": "29-Feb-2024",
            "underlying": "APOLLOHOSP",
            "identifier": "OPTSTKAPOLLOHOSP29-02-2024CE5400.00",
            "openInterest": 0,
            "changeinOpenInterest": 0,
            "pchangeinOpenInterest": 0,
            "totalTradedVolume": 0,
            "impliedVolatility": 0,
            "lastPrice": 0,
            "change": 0,
            "pChange": 0,
            "totalBuyQuantity": 1250,
            "totalSellQuantity": 1250,
            "bidQty": 375,
            "bidprice": 445.3,
            "askQty": 375,
            "askPrice": 630,
            "underlyingValue": 5807.45
        }
    },
    {
        "strikePrice": 5450,
        "expiryDate": "29-Feb-2024",
        "CE": {
            "strikePrice": 5450,
            "expiryDate": "29-Feb-2024",
            "underlying": "APOLLOHOSP",
            "identifier": "OPTSTKAPOLLOHOSP29-02-2024CE5450.00",
            "openInterest": 0,
            "changeinOpenInterest": 0,
            "pchangeinOpenInterest": 0,
            "totalTradedVolume": 0,
            "impliedVolatility": 0,
            "lastPrice": 0,
            "change": 0,
            "pChange": 0,
            "totalBuyQuantity": 1250,
            "totalSellQuantity": 375,
            "bidQty": 375,
            "bidprice": 385.1,
            "askQty": 375,
            "askPrice": 712.7,
            "underlyingValue": 5807.45
        },
        "PE": {
            "strikePrice": 5450,
            "expiryDate": "29-Feb-2024",
            "underlying": "APOLLOHOSP",
            "identifier": "OPTSTKAPOLLOHOSP29-02-2024PE5450.00",
            "openInterest": 0,
            "changeinOpenInterest": 0,
            "pchangeinOpenInterest": 0,
            "totalTradedVolume": 0,
            "impliedVolatility": 0,
            "lastPrice": 0,
            "change": 0,
            "pChange": 0,
            "totalBuyQuantity": 1500,
            "totalSellQuantity": 0,
            "bidQty": 1500,
            "bidprice": 5.15,
            "askQty": 0,
            "askPrice": 0,
            "underlyingValue": 5807.45
        }
    },
    {
        "strikePrice": 5500,
        "expiryDate": "29-Feb-2024",
        "PE": {
            "strikePrice": 5500,
            "expiryDate": "29-Feb-2024",
            "underlying": "APOLLOHOSP",
            "identifier": "OPTSTKAPOLLOHOSP29-02-2024PE5500.00",
            "openInterest": 30,
            "changeinOpenInterest": 20,
            "pchangeinOpenInterest": 200,
            "totalTradedVolume": 20,
            "impliedVolatility": 27.02,
            "lastPrice": 80,
            "change": -1.8499999999999943,
            "pChange": -2.26023213194868,
            "totalBuyQuantity": 2875,
            "totalSellQuantity": 500,
            "bidQty": 125,
            "bidprice": 68.55,
            "askQty": 125,
            "askPrice": 94.8,
            "underlyingValue": 5807.45
        },
        "CE": {
            "strikePrice": 5500,
            "expiryDate": "29-Feb-2024",
            "underlying": "APOLLOHOSP",
            "identifier": "OPTSTKAPOLLOHOSP29-02-2024CE5500.00",
            "openInterest": 0,
            "changeinOpenInterest": 0,
            "pchangeinOpenInterest": 0,
            "totalTradedVolume": 0,
            "impliedVolatility": 0,
            "lastPrice": 0,
            "change": 0,
            "pChange": 0,
            "totalBuyQuantity": 1250,
            "totalSellQuantity": 1500,
            "bidQty": 375,
            "bidprice": 409.6,
            "askQty": 250,
            "askPrice": 538.35,
            "underlyingValue": 5807.45
        }
    },
    {
        "strikePrice": 5550,
        "expiryDate": "29-Feb-2024",
        "PE": {
            "strikePrice": 5550,
            "expiryDate": "29-Feb-2024",
            "underlying": "APOLLOHOSP",
            "identifier": "OPTSTKAPOLLOHOSP29-02-2024PE5550.00",
            "openInterest": 0,
            "changeinOpenInterest": 0,
            "pchangeinOpenInterest": 0,
            "totalTradedVolume": 0,
            "impliedVolatility": 0,
            "lastPrice": 0,
            "change": 0,
            "pChange": 0,
            "totalBuyQuantity": 1500,
            "totalSellQuantity": 0,
            "bidQty": 1500,
            "bidprice": 11,
            "askQty": 0,
            "askPrice": 0,
            "underlyingValue": 5807.45
        },
        "CE": {
            "strikePrice": 5550,
            "expiryDate": "29-Feb-2024",
            "underlying": "APOLLOHOSP",
            "identifier": "OPTSTKAPOLLOHOSP29-02-2024CE5550.00",
            "openInterest": 0,
            "changeinOpenInterest": 0,
            "pchangeinOpenInterest": 0,
            "totalTradedVolume": 0,
            "impliedVolatility": 0,
            "lastPrice": 0,
            "change": 0,
            "pChange": 0,
            "totalBuyQuantity": 1250,
            "totalSellQuantity": 375,
            "bidQty": 375,
            "bidprice": 289.5,
            "askQty": 375,
            "askPrice": 611.5,
            "underlyingValue": 5807.45
        }
    },
    {
        "strikePrice": 5600,
        "expiryDate": "29-Feb-2024",
        "PE": {
            "strikePrice": 5600,
            "expiryDate": "29-Feb-2024",
            "underlying": "APOLLOHOSP",
            "identifier": "OPTSTKAPOLLOHOSP29-02-2024PE5600.00",
            "openInterest": 1,
            "changeinOpenInterest": 0,
            "pchangeinOpenInterest": 0,
            "totalTradedVolume": 0,
            "impliedVolatility": 0,
            "lastPrice": 100,
            "change": 0,
            "pChange": 0,
            "totalBuyQuantity": 1625,
            "totalSellQuantity": 125,
            "bidQty": 125,
            "bidprice": 93.2,
            "askQty": 125,
            "askPrice": 150,
            "underlyingValue": 5807.45
        },
        "CE": {
            "strikePrice": 5600,
            "expiryDate": "29-Feb-2024",
            "underlying": "APOLLOHOSP",
            "identifier": "OPTSTKAPOLLOHOSP29-02-2024CE5600.00",
            "openInterest": 0,
            "changeinOpenInterest": 0,
            "pchangeinOpenInterest": 0,
            "totalTradedVolume": 0,
            "impliedVolatility": 0,
            "lastPrice": 0,
            "change": 0,
            "pChange": 0,
            "totalBuyQuantity": 1625,
            "totalSellQuantity": 1500,
            "bidQty": 250,
            "bidprice": 264.4,
            "askQty": 250,
            "askPrice": 494.05,
            "underlyingValue": 5807.45
        }
    },
    {
        "strikePrice": 5650,
        "expiryDate": "29-Feb-2024",
        "PE": {
            "strikePrice": 5650,
            "expiryDate": "29-Feb-2024",
            "underlying": "APOLLOHOSP",
            "identifier": "OPTSTKAPOLLOHOSP29-02-2024PE5650.00",
            "openInterest": 0,
            "changeinOpenInterest": 0,
            "pchangeinOpenInterest": 0,
            "totalTradedVolume": 0,
            "impliedVolatility": 0,
            "lastPrice": 0,
            "change": 0,
            "pChange": 0,
            "totalBuyQuantity": 1500,
            "totalSellQuantity": 0,
            "bidQty": 1500,
            "bidprice": 31,
            "askQty": 0,
            "askPrice": 0,
            "underlyingValue": 5807.45
        },
        "CE": {
            "strikePrice": 5650,
            "expiryDate": "29-Feb-2024",
            "underlying": "APOLLOHOSP",
            "identifier": "OPTSTKAPOLLOHOSP29-02-2024CE5650.00",
            "openInterest": 0,
            "changeinOpenInterest": 0,
            "pchangeinOpenInterest": 0,
            "totalTradedVolume": 0,
            "impliedVolatility": 0,
            "lastPrice": 0,
            "change": 0,
            "pChange": 0,
            "totalBuyQuantity": 1500,
            "totalSellQuantity": 0,
            "bidQty": 375,
            "bidprice": 215.35,
            "askQty": 0,
            "askPrice": 0,
            "underlyingValue": 5807.45
        }
    },
    {
        "strikePrice": 5700,
        "expiryDate": "29-Feb-2024",
        "PE": {
            "strikePrice": 5700,
            "expiryDate": "29-Feb-2024",
            "underlying": "APOLLOHOSP",
            "identifier": "OPTSTKAPOLLOHOSP29-02-2024PE5700.00",
            "openInterest": 0,
            "changeinOpenInterest": 0,
            "pchangeinOpenInterest": 0,
            "totalTradedVolume": 0,
            "impliedVolatility": 0,
            "lastPrice": 0,
            "change": 0,
            "pChange": 0,
            "totalBuyQuantity": 375,
            "totalSellQuantity": 0,
            "bidQty": 250,
            "bidprice": 119.2,
            "askQty": 0,
            "askPrice": 0,
            "underlyingValue": 5807.45
        },
        "CE": {
            "strikePrice": 5700,
            "expiryDate": "29-Feb-2024",
            "underlying": "APOLLOHOSP",
            "identifier": "OPTSTKAPOLLOHOSP29-02-2024CE5700.00",
            "openInterest": 0,
            "changeinOpenInterest": 0,
            "pchangeinOpenInterest": 0,
            "totalTradedVolume": 0,
            "impliedVolatility": 0,
            "lastPrice": 0,
            "change": 0,
            "pChange": 0,
            "totalBuyQuantity": 1500,
            "totalSellQuantity": 1375,
            "bidQty": 375,
            "bidprice": 189.2,
            "askQty": 125,
            "askPrice": 376.85,
            "underlyingValue": 5807.45
        }
    },
    {
        "strikePrice": 5750,
        "expiryDate": "29-Feb-2024",
        "PE": {
            "strikePrice": 5750,
            "expiryDate": "29-Feb-2024",
            "underlying": "APOLLOHOSP",
            "identifier": "OPTSTKAPOLLOHOSP29-02-2024PE5750.00",
            "openInterest": 0,
            "changeinOpenInterest": 0,
            "pchangeinOpenInterest": 0,
            "totalTradedVolume": 0,
            "impliedVolatility": 0,
            "lastPrice": 0,
            "change": 0,
            "pChange": 0,
            "totalBuyQuantity": 125,
            "totalSellQuantity": 0,
            "bidQty": 125,
            "bidprice": 133.25,
            "askQty": 0,
            "askPrice": 0,
            "underlyingValue": 5807.45
        },
        "CE": {
            "strikePrice": 5750,
            "expiryDate": "29-Feb-2024",
            "underlying": "APOLLOHOSP",
            "identifier": "OPTSTKAPOLLOHOSP29-02-2024CE5750.00",
            "openInterest": 0,
            "changeinOpenInterest": 0,
            "pchangeinOpenInterest": 0,
            "totalTradedVolume": 0,
            "impliedVolatility": 0,
            "lastPrice": 0,
            "change": 0,
            "pChange": 0,
            "totalBuyQuantity": 1750,
            "totalSellQuantity": 1250,
            "bidQty": 875,
            "bidprice": 159.1,
            "askQty": 375,
            "askPrice": 423.8,
            "underlyingValue": 5807.45
        }
    },
    {
        "strikePrice": 5800,
        "expiryDate": "29-Feb-2024",
        "CE": {
            "strikePrice": 5800,
            "expiryDate": "29-Feb-2024",
            "underlying": "APOLLOHOSP",
            "identifier": "OPTSTKAPOLLOHOSP29-02-2024CE5800.00",
            "openInterest": 3,
            "changeinOpenInterest": 0,
            "pchangeinOpenInterest": 0,
            "totalTradedVolume": 2,
            "impliedVolatility": 22.16,
            "lastPrice": 229.35,
            "change": -12.550000000000011,
            "pChange": -5.188094253823898,
            "totalBuyQuantity": 625,
            "totalSellQuantity": 1375,
            "bidQty": 125,
            "bidprice": 179.6,
            "askQty": 125,
            "askPrice": 259.4,
            "underlyingValue": 5807.45
        },
        "PE": {
            "strikePrice": 5800,
            "expiryDate": "29-Feb-2024",
            "underlying": "APOLLOHOSP",
            "identifier": "OPTSTKAPOLLOHOSP29-02-2024PE5800.00",
            "openInterest": 0,
            "changeinOpenInterest": 0,
            "pchangeinOpenInterest": 0,
            "totalTradedVolume": 0,
            "impliedVolatility": 0,
            "lastPrice": 0,
            "change": 0,
            "pChange": 0,
            "totalBuyQuantity": 375,
            "totalSellQuantity": 0,
            "bidQty": 125,
            "bidprice": 164.5,
            "askQty": 0,
            "askPrice": 0,
            "underlyingValue": 5807.45
        }
    },
    {
        "strikePrice": 5850,
        "expiryDate": "29-Feb-2024",
        "PE": {
            "strikePrice": 5850,
            "expiryDate": "29-Feb-2024",
            "underlying": "APOLLOHOSP",
            "identifier": "OPTSTKAPOLLOHOSP29-02-2024PE5850.00",
            "openInterest": 0,
            "changeinOpenInterest": 0,
            "pchangeinOpenInterest": 0,
            "totalTradedVolume": 0,
            "impliedVolatility": 0,
            "lastPrice": 0,
            "change": 0,
            "pChange": 0,
            "totalBuyQuantity": 125,
            "totalSellQuantity": 0,
            "bidQty": 125,
            "bidprice": 170.85,
            "askQty": 0,
            "askPrice": 0,
            "underlyingValue": 5807.45
        },
        "CE": {
            "strikePrice": 5850,
            "expiryDate": "29-Feb-2024",
            "underlying": "APOLLOHOSP",
            "identifier": "OPTSTKAPOLLOHOSP29-02-2024CE5850.00",
            "openInterest": 0,
            "changeinOpenInterest": 0,
            "pchangeinOpenInterest": 0,
            "totalTradedVolume": 0,
            "impliedVolatility": 0,
            "lastPrice": 0,
            "change": 0,
            "pChange": 0,
            "totalBuyQuantity": 500,
            "totalSellQuantity": 1125,
            "bidQty": 500,
            "bidprice": 101,
            "askQty": 125,
            "askPrice": 263.3,
            "underlyingValue": 5807.45
        }
    },
    {
        "strikePrice": 5900,
        "expiryDate": "29-Feb-2024",
        "CE": {
            "strikePrice": 5900,
            "expiryDate": "29-Feb-2024",
            "underlying": "APOLLOHOSP",
            "identifier": "OPTSTKAPOLLOHOSP29-02-2024CE5900.00",
            "openInterest": 0,
            "changeinOpenInterest": 0,
            "pchangeinOpenInterest": 0,
            "totalTradedVolume": 0,
            "impliedVolatility": 0,
            "lastPrice": 0,
            "change": 0,
            "pChange": 0,
            "totalBuyQuantity": 500,
            "totalSellQuantity": 0,
            "bidQty": 500,
            "bidprice": 81,
            "askQty": 0,
            "askPrice": 0,
            "underlyingValue": 5807.45
        },
        "PE": {
            "strikePrice": 5900,
            "expiryDate": "29-Feb-2024",
            "underlying": "APOLLOHOSP",
            "identifier": "OPTSTKAPOLLOHOSP29-02-2024PE5900.00",
            "openInterest": 0,
            "changeinOpenInterest": 0,
            "pchangeinOpenInterest": 0,
            "totalTradedVolume": 0,
            "impliedVolatility": 0,
            "lastPrice": 0,
            "change": 0,
            "pChange": 0,
            "totalBuyQuantity": 1250,
            "totalSellQuantity": 0,
            "bidQty": 875,
            "bidprice": 84.8,
            "askQty": 0,
            "askPrice": 0,
            "underlyingValue": 5807.45
        }
    },
    {
        "strikePrice": 5950,
        "expiryDate": "29-Feb-2024",
        "PE": {
            "strikePrice": 5950,
            "expiryDate": "29-Feb-2024",
            "underlying": "APOLLOHOSP",
            "identifier": "OPTSTKAPOLLOHOSP29-02-2024PE5950.00",
            "openInterest": 0,
            "changeinOpenInterest": 0,
            "pchangeinOpenInterest": 0,
            "totalTradedVolume": 0,
            "impliedVolatility": 0,
            "lastPrice": 0,
            "change": 0,
            "pChange": 0,
            "totalBuyQuantity": 1250,
            "totalSellQuantity": 375,
            "bidQty": 375,
            "bidprice": 122.1,
            "askQty": 375,
            "askPrice": 371.35,
            "underlyingValue": 5807.45
        },
        "CE": {
            "strikePrice": 5950,
            "expiryDate": "29-Feb-2024",
            "underlying": "APOLLOHOSP",
            "identifier": "OPTSTKAPOLLOHOSP29-02-2024CE5950.00",
            "openInterest": 0,
            "changeinOpenInterest": 0,
            "pchangeinOpenInterest": 0,
            "totalTradedVolume": 0,
            "impliedVolatility": 0,
            "lastPrice": 0,
            "change": 0,
            "pChange": 0,
            "totalBuyQuantity": 500,
            "totalSellQuantity": 0,
            "bidQty": 500,
            "bidprice": 65,
            "askQty": 0,
            "askPrice": 0,
            "underlyingValue": 5807.45
        }
    },
    {
        "strikePrice": 6000,
        "expiryDate": "29-Feb-2024",
        "PE": {
            "strikePrice": 6000,
            "expiryDate": "29-Feb-2024",
            "underlying": "APOLLOHOSP",
            "identifier": "OPTSTKAPOLLOHOSP29-02-2024PE6000.00",
            "openInterest": 0,
            "changeinOpenInterest": 0,
            "pchangeinOpenInterest": 0,
            "totalTradedVolume": 0,
            "impliedVolatility": 0,
            "lastPrice": 0,
            "change": 0,
            "pChange": 0,
            "totalBuyQuantity": 1375,
            "totalSellQuantity": 1375,
            "bidQty": 125,
            "bidprice": 148.3,
            "askQty": 125,
            "askPrice": 343.75,
            "underlyingValue": 5807.45
        },
        "CE": {
            "strikePrice": 6000,
            "expiryDate": "29-Feb-2024",
            "underlying": "APOLLOHOSP",
            "identifier": "OPTSTKAPOLLOHOSP29-02-2024CE6000.00",
            "openInterest": 24,
            "changeinOpenInterest": 2,
            "pchangeinOpenInterest": 9.090909090909092,
            "totalTradedVolume": 4,
            "impliedVolatility": 25.11,
            "lastPrice": 160.7,
            "change": -21.400000000000006,
            "pChange": -11.751784733662825,
            "totalBuyQuantity": 1000,
            "totalSellQuantity": 375,
            "bidQty": 125,
            "bidprice": 136.65,
            "askQty": 125,
            "askPrice": 165.8,
            "underlyingValue": 5807.45
        }
    },
    {
        "strikePrice": 6050,
        "expiryDate": "29-Feb-2024",
        "PE": {
            "strikePrice": 6050,
            "expiryDate": "29-Feb-2024",
            "underlying": "APOLLOHOSP",
            "identifier": "OPTSTKAPOLLOHOSP29-02-2024PE6050.00",
            "openInterest": 0,
            "changeinOpenInterest": 0,
            "pchangeinOpenInterest": 0,
            "totalTradedVolume": 0,
            "impliedVolatility": 0,
            "lastPrice": 0,
            "change": 0,
            "pChange": 0,
            "totalBuyQuantity": 1250,
            "totalSellQuantity": 0,
            "bidQty": 375,
            "bidprice": 184.15,
            "askQty": 0,
            "askPrice": 0,
            "underlyingValue": 5807.45
        },
        "CE": {
            "strikePrice": 6050,
            "expiryDate": "29-Feb-2024",
            "underlying": "APOLLOHOSP",
            "identifier": "OPTSTKAPOLLOHOSP29-02-2024CE6050.00",
            "openInterest": 0,
            "changeinOpenInterest": 0,
            "pchangeinOpenInterest": 0,
            "totalTradedVolume": 0,
            "impliedVolatility": 0,
            "lastPrice": 0,
            "change": 0,
            "pChange": 0,
            "totalBuyQuantity": 500,
            "totalSellQuantity": 0,
            "bidQty": 500,
            "bidprice": 41,
            "askQty": 0,
            "askPrice": 0,
            "underlyingValue": 5807.45
        }
    },
    {
        "strikePrice": 6100,
        "expiryDate": "29-Feb-2024",
        "CE": {
            "strikePrice": 6100,
            "expiryDate": "29-Feb-2024",
            "underlying": "APOLLOHOSP",
            "identifier": "OPTSTKAPOLLOHOSP29-02-2024CE6100.00",
            "openInterest": 0,
            "changeinOpenInterest": 0,
            "pchangeinOpenInterest": 0,
            "totalTradedVolume": 0,
            "impliedVolatility": 0,
            "lastPrice": 0,
            "change": 0,
            "pChange": 0,
            "totalBuyQuantity": 500,
            "totalSellQuantity": 0,
            "bidQty": 500,
            "bidprice": 31,
            "askQty": 0,
            "askPrice": 0,
            "underlyingValue": 5807.45
        },
        "PE": {
            "strikePrice": 6100,
            "expiryDate": "29-Feb-2024",
            "underlying": "APOLLOHOSP",
            "identifier": "OPTSTKAPOLLOHOSP29-02-2024PE6100.00",
            "openInterest": 0,
            "changeinOpenInterest": 0,
            "pchangeinOpenInterest": 0,
            "totalTradedVolume": 0,
            "impliedVolatility": 0,
            "lastPrice": 0,
            "change": 0,
            "pChange": 0,
            "totalBuyQuantity": 1250,
            "totalSellQuantity": 0,
            "bidQty": 375,
            "bidprice": 216.95,
            "askQty": 0,
            "askPrice": 0,
            "underlyingValue": 5807.45
        }
    },
    {
        "strikePrice": 6150,
        "expiryDate": "29-Feb-2024",
        "PE": {
            "strikePrice": 6150,
            "expiryDate": "29-Feb-2024",
            "underlying": "APOLLOHOSP",
            "identifier": "OPTSTKAPOLLOHOSP29-02-2024PE6150.00",
            "openInterest": 0,
            "changeinOpenInterest": 0,
            "pchangeinOpenInterest": 0,
            "totalTradedVolume": 0,
            "impliedVolatility": 0,
            "lastPrice": 0,
            "change": 0,
            "pChange": 0,
            "totalBuyQuantity": 1250,
            "totalSellQuantity": 0,
            "bidQty": 375,
            "bidprice": 263.1,
            "askQty": 0,
            "askPrice": 0,
            "underlyingValue": 5807.45
        },
        "CE": {
            "strikePrice": 6150,
            "expiryDate": "29-Feb-2024",
            "underlying": "APOLLOHOSP",
            "identifier": "OPTSTKAPOLLOHOSP29-02-2024CE6150.00",
            "openInterest": 0,
            "changeinOpenInterest": 0,
            "pchangeinOpenInterest": 0,
            "totalTradedVolume": 0,
            "impliedVolatility": 0,
            "lastPrice": 0,
            "change": 0,
            "pChange": 0,
            "totalBuyQuantity": 500,
            "totalSellQuantity": 0,
            "bidQty": 500,
            "bidprice": 21,
            "askQty": 0,
            "askPrice": 0,
            "underlyingValue": 5807.45
        }
    },
    {
        "strikePrice": 6200,
        "expiryDate": "29-Feb-2024",
        "CE": {
            "strikePrice": 6200,
            "expiryDate": "29-Feb-2024",
            "underlying": "APOLLOHOSP",
            "identifier": "OPTSTKAPOLLOHOSP29-02-2024CE6200.00",
            "openInterest": 4,
            "changeinOpenInterest": 0,
            "pchangeinOpenInterest": 0,
            "totalTradedVolume": 1,
            "impliedVolatility": 28.37,
            "lastPrice": 119.7,
            "change": 9.700000000000003,
            "pChange": 8.81818181818182,
            "totalBuyQuantity": 625,
            "totalSellQuantity": 125,
            "bidQty": 500,
            "bidprice": 21,
            "askQty": 125,
            "askPrice": 216.8,
            "underlyingValue": 5807.45
        },
        "PE": {
            "strikePrice": 6200,
            "expiryDate": "29-Feb-2024",
            "underlying": "APOLLOHOSP",
            "identifier": "OPTSTKAPOLLOHOSP29-02-2024PE6200.00",
            "openInterest": 0,
            "changeinOpenInterest": 0,
            "pchangeinOpenInterest": 0,
            "totalTradedVolume": 0,
            "impliedVolatility": 0,
            "lastPrice": 0,
            "change": 0,
            "pChange": 0,
            "totalBuyQuantity": 1250,
            "totalSellQuantity": 0,
            "bidQty": 375,
            "bidprice": 303.35,
            "askQty": 0,
            "askPrice": 0,
            "underlyingValue": 5807.45
        }
    },
    {
        "strikePrice": 6250,
        "expiryDate": "29-Feb-2024",
        "PE": {
            "strikePrice": 6250,
            "expiryDate": "29-Feb-2024",
            "underlying": "APOLLOHOSP",
            "identifier": "OPTSTKAPOLLOHOSP29-02-2024PE6250.00",
            "openInterest": 0,
            "changeinOpenInterest": 0,
            "pchangeinOpenInterest": 0,
            "totalTradedVolume": 0,
            "impliedVolatility": 0,
            "lastPrice": 0,
            "change": 0,
            "pChange": 0,
            "totalBuyQuantity": 6250,
            "totalSellQuantity": 0,
            "bidQty": 375,
            "bidprice": 357.4,
            "askQty": 0,
            "askPrice": 0,
            "underlyingValue": 5807.45
        },
        "CE": {
            "strikePrice": 6250,
            "expiryDate": "29-Feb-2024",
            "underlying": "APOLLOHOSP",
            "identifier": "OPTSTKAPOLLOHOSP29-02-2024CE6250.00",
            "openInterest": 0,
            "changeinOpenInterest": 0,
            "pchangeinOpenInterest": 0,
            "totalTradedVolume": 0,
            "impliedVolatility": 0,
            "lastPrice": 0,
            "change": 0,
            "pChange": 0,
            "totalBuyQuantity": 500,
            "totalSellQuantity": 0,
            "bidQty": 500,
            "bidprice": 11,
            "askQty": 0,
            "askPrice": 0,
            "underlyingValue": 5807.45
        }
    }
]