[
    {
        "strikePrice": 124,
        "expiryDate": "29-Feb-2024",
        "CE": {
            "strikePrice": 124,
            "expiryDate": "29-Feb-2024",
            "underlying": "TATASTEEL",
            "identifier": "OPTSTKTATASTEEL29-02-2024CE124.00",
            "openInterest": 0,
            "changeinOpenInterest": 0,
            "pchangeinOpenInterest": 0,
            "totalTradedVolume": 0,
            "impliedVolatility": 0,
            "lastPrice": 0,
            "change": 0,
            "pChange": 0,
            "totalBuyQuantity": 220000,
            "totalSellQuantity": 220000,
            "bidQty": 16500,
            "bidprice": 11.35,
            "askQty": 16500,
            "askPrice": 14,
            "underlyingValue": 133.9
        },
        "PE": {
            "strikePrice": 124,
            "expiryDate": "29-Feb-2024",
            "underlying": "TATASTEEL",
            "identifier": "OPTSTKTATASTEEL29-02-2024PE124.00",
            "openInterest": 24,
            "changeinOpenInterest": 1,
            "pchangeinOpenInterest": 4.3478260869565215,
            "totalTradedVolume": 2,
            "impliedVolatility": 32.83,
            "lastPrice": 1.65,
            "change": -0.15000000000000013,
            "pChange": -8.333333333333341,
            "totalBuyQuantity": 38500,
            "totalSellQuantity": 176000,
            "bidQty": 5500,
            "bidprice": 0.3,
            "askQty": 5500,
            "askPrice": 2.55,
            "underlyingValue": 133.9
        }
    },
    {
        "strikePrice": 125,
        "expiryDate": "29-Feb-2024",
        "PE": {
            "strikePrice": 125,
            "expiryDate": "29-Feb-2024",
            "underlying": "TATASTEEL",
            "identifier": "OPTSTKTATASTEEL29-02-2024PE125.00",
            "openInterest": 780,
            "changeinOpenInterest": -15,
            "pchangeinOpenInterest": -1.8867924528301887,
            "totalTradedVolume": 276,
            "impliedVolatility": 34.09,
            "lastPrice": 2.05,
            "change": -0.050000000000000266,
            "pChange": -2.380952380952394,
            "totalBuyQuantity": 467500,
            "totalSellQuantity": 225500,
            "bidQty": 16500,
            "bidprice": 1.9,
            "askQty": 5500,
            "askPrice": 2.05,
            "underlyingValue": 133.9
        },
        "CE": {
            "strikePrice": 125,
            "expiryDate": "29-Feb-2024",
            "underlying": "TATASTEEL",
            "identifier": "OPTSTKTATASTEEL29-02-2024CE125.00",
            "openInterest": 120,
            "changeinOpenInterest": 24,
            "pchangeinOpenInterest": 25,
            "totalTradedVolume": 85,
            "impliedVolatility": 33.24,
            "lastPrice": 12.2,
            "change": -0.25,
            "pChange": -2.0080321285140563,
            "totalBuyQuantity": 319000,
            "totalSellQuantity": 308000,
            "bidQty": 5500,
            "bidprice": 11.8,
            "askQty": 5500,
            "askPrice": 12.2,
            "underlyingValue": 133.9
        }
    },
    {
        "strikePrice": 126,
        "expiryDate": "29-Feb-2024",
        "PE": {
            "strikePrice": 126,
            "expiryDate": "29-Feb-2024",
            "underlying": "TATASTEEL",
            "identifier": "OPTSTKTATASTEEL29-02-2024PE126.00",
            "openInterest": 8,
            "changeinOpenInterest": 5,
            "pchangeinOpenInterest": 166.66666666666666,
            "totalTradedVolume": 11,
            "impliedVolatility": 33.61,
            "lastPrice": 2.25,
            "change": 0.1499999999999999,
            "pChange": 7.142857142857138,
            "totalBuyQuantity": 341000,
            "totalSellQuantity": 0,
            "bidQty": 165000,
            "bidprice": 0.9,
            "askQty": 0,
            "askPrice": 0,
            "underlyingValue": 133.9
        },
        "CE": {
            "strikePrice": 126,
            "expiryDate": "29-Feb-2024",
            "underlying": "TATASTEEL",
            "identifier": "OPTSTKTATASTEEL29-02-2024CE126.00",
            "openInterest": 0,
            "changeinOpenInterest": 0,
            "pchangeinOpenInterest": 0,
            "totalTradedVolume": 0,
            "impliedVolatility": 0,
            "lastPrice": 0,
            "change": 0,
            "pChange": 0,
            "totalBuyQuantity": 225500,
            "totalSellQuantity": 220000,
            "bidQty": 5500,
            "bidprice": 9.5,
            "askQty": 38500,
            "askPrice": 12.95,
            "underlyingValue": 133.9
        }
    },
    {
        "strikePrice": 127,
        "expiryDate": "29-Feb-2024",
        "PE": {
            "strikePrice": 127,
            "expiryDate": "29-Feb-2024",
            "underlying": "TATASTEEL",
            "identifier": "OPTSTKTATASTEEL29-02-2024PE127.00",
            "openInterest": 6,
            "changeinOpenInterest": 0,
            "pchangeinOpenInterest": 0,
            "totalTradedVolume": 2,
            "impliedVolatility": 32.67,
            "lastPrice": 2.4,
            "change": -0.20000000000000018,
            "pChange": -7.692307692307699,
            "totalBuyQuantity": 181500,
            "totalSellQuantity": 0,
            "bidQty": 165000,
            "bidprice": 1.05,
            "askQty": 0,
            "askPrice": 0,
            "underlyingValue": 133.9
        },
        "CE": {
            "strikePrice": 127,
            "expiryDate": "29-Feb-2024",
            "underlying": "TATASTEEL",
            "identifier": "OPTSTKTATASTEEL29-02-2024CE127.00",
            "openInterest": 0,
            "changeinOpenInterest": 0,
            "pchangeinOpenInterest": 0,
            "totalTradedVolume": 0,
            "impliedVolatility": 0,
            "lastPrice": 0,
            "change": 0,
            "pChange": 0,
            "totalBuyQuantity": 220000,
            "totalSellQuantity": 220000,
            "bidQty": 16500,
            "bidprice": 8.6,
            "askQty": 16500,
            "askPrice": 13.3,
            "underlyingValue": 133.9
        }
    },
    {
        "strikePrice": 128,
        "expiryDate": "29-Feb-2024",
        "PE": {
            "strikePrice": 128,
            "expiryDate": "29-Feb-2024",
            "underlying": "TATASTEEL",
            "identifier": "OPTSTKTATASTEEL29-02-2024PE128.00",
            "openInterest": 37,
            "changeinOpenInterest": 5,
            "pchangeinOpenInterest": 15.625,
            "totalTradedVolume": 29,
            "impliedVolatility": 33.96,
            "lastPrice": 2.9,
            "change": 0.10000000000000009,
            "pChange": 3.5714285714285747,
            "totalBuyQuantity": 198000,
            "totalSellQuantity": 176000,
            "bidQty": 11000,
            "bidprice": 2.85,
            "askQty": 5500,
            "askPrice": 3.95,
            "underlyingValue": 133.9
        },
        "CE": {
            "strikePrice": 128,
            "expiryDate": "29-Feb-2024",
            "underlying": "TATASTEEL",
            "identifier": "OPTSTKTATASTEEL29-02-2024CE128.00",
            "openInterest": 2,
            "changeinOpenInterest": 0,
            "pchangeinOpenInterest": 0,
            "totalTradedVolume": 0,
            "impliedVolatility": 0,
            "lastPrice": 10,
            "change": 0,
            "pChange": 0,
            "totalBuyQuantity": 236500,
            "totalSellQuantity": 236500,
            "bidQty": 16500,
            "bidprice": 9.35,
            "askQty": 16500,
            "askPrice": 11.5,
            "underlyingValue": 133.9
        }
    },
    {
        "strikePrice": 129,
        "expiryDate": "29-Feb-2024",
        "CE": {
            "strikePrice": 129,
            "expiryDate": "29-Feb-2024",
            "underlying": "TATASTEEL",
            "identifier": "OPTSTKTATASTEEL29-02-2024CE129.00",
            "openInterest": 6,
            "changeinOpenInterest": 0,
            "pchangeinOpenInterest": 0,
            "totalTradedVolume": 0,
            "impliedVolatility": 0,
            "lastPrice": 9.6,
            "change": 0,
            "pChange": 0,
            "totalBuyQuantity": 55000,
            "totalSellQuantity": 225500,
            "bidQty": 38500,
            "bidprice": 8.35,
            "askQty": 5500,
            "askPrice": 10.4,
            "underlyingValue": 133.9
        },
        "PE": {
            "strikePrice": 129,
            "expiryDate": "29-Feb-2024",
            "underlying": "TATASTEEL",
            "identifier": "OPTSTKTATASTEEL29-02-2024PE129.00",
            "openInterest": 30,
            "changeinOpenInterest": 10,
            "pchangeinOpenInterest": 50,
            "totalTradedVolume": 16,
            "impliedVolatility": 31.79,
            "lastPrice": 2.9,
            "change": -0.3999999999999999,
            "pChange": -12.12121212121212,
            "totalBuyQuantity": 390500,
            "totalSellQuantity": 225500,
            "bidQty": 5500,
            "bidprice": 2.75,
            "askQty": 5500,
            "askPrice": 3.8,
            "underlyingValue": 133.9
        }
    },
    {
        "strikePrice": 130,
        "expiryDate": "29-Feb-2024",
        "PE": {
            "strikePrice": 130,
            "expiryDate": "29-Feb-2024",
            "underlying": "TATASTEEL",
            "identifier": "OPTSTKTATASTEEL29-02-2024PE130.00",
            "openInterest": 671,
            "changeinOpenInterest": 14,
            "pchangeinOpenInterest": 2.13089802130898,
            "totalTradedVolume": 188,
            "impliedVolatility": 34.25,
            "lastPrice": 3.65,
            "change": 0,
            "pChange": 0,
            "totalBuyQuantity": 627000,
            "totalSellQuantity": 583000,
            "bidQty": 5500,
            "bidprice": 3.3,
            "askQty": 5500,
            "askPrice": 3.75,
            "underlyingValue": 133.9
        },
        "CE": {
            "strikePrice": 130,
            "expiryDate": "29-Feb-2024",
            "underlying": "TATASTEEL",
            "identifier": "OPTSTKTATASTEEL29-02-2024CE130.00",
            "openInterest": 543,
            "changeinOpenInterest": -27,
            "pchangeinOpenInterest": -4.7368421052631575,
            "totalTradedVolume": 226,
            "impliedVolatility": 33.84,
            "lastPrice": 8.9,
            "change": -0.40000000000000036,
            "pChange": -4.3010752688172085,
            "totalBuyQuantity": 198000,
            "totalSellQuantity": 418000,
            "bidQty": 5500,
            "bidprice": 8.6,
            "askQty": 11000,
            "askPrice": 8.9,
            "underlyingValue": 133.9
        }
    },
    {
        "strikePrice": 131,
        "expiryDate": "29-Feb-2024",
        "PE": {
            "strikePrice": 131,
            "expiryDate": "29-Feb-2024",
            "underlying": "TATASTEEL",
            "identifier": "OPTSTKTATASTEEL29-02-2024PE131.00",
            "openInterest": 27,
            "changeinOpenInterest": 13,
            "pchangeinOpenInterest": 92.85714285714286,
            "totalTradedVolume": 41,
            "impliedVolatility": 34.91,
            "lastPrice": 4.15,
            "change": 0.35000000000000053,
            "pChange": 9.210526315789489,
            "totalBuyQuantity": 236500,
            "totalSellQuantity": 77000,
            "bidQty": 5500,
            "bidprice": 3.6,
            "askQty": 5500,
            "askPrice": 4.15,
            "underlyingValue": 133.9
        },
        "CE": {
            "strikePrice": 131,
            "expiryDate": "29-Feb-2024",
            "underlying": "TATASTEEL",
            "identifier": "OPTSTKTATASTEEL29-02-2024CE131.00",
            "openInterest": 20,
            "changeinOpenInterest": 0,
            "pchangeinOpenInterest": 0,
            "totalTradedVolume": 0,
            "impliedVolatility": 0,
            "lastPrice": 8.85,
            "change": 0,
            "pChange": 0,
            "totalBuyQuantity": 60500,
            "totalSellQuantity": 242000,
            "bidQty": 5500,
            "bidprice": 8,
            "askQty": 5500,
            "askPrice": 8.4,
            "underlyingValue": 133.9
        }
    },
    {
        "strikePrice": 132,
        "expiryDate": "29-Feb-2024",
        "PE": {
            "strikePrice": 132,
            "expiryDate": "29-Feb-2024",
            "underlying": "TATASTEEL",
            "identifier": "OPTSTKTATASTEEL29-02-2024PE132.00",
            "openInterest": 71,
            "changeinOpenInterest": 10,
            "pchangeinOpenInterest": 16.39344262295082,
            "totalTradedVolume": 42,
            "impliedVolatility": 34.51,
            "lastPrice": 4.5,
            "change": -0.04999999999999982,
            "pChange": -1.098901098901095,
            "totalBuyQuantity": 473000,
            "totalSellQuantity": 445500,
            "bidQty": 5500,
            "bidprice": 4.05,
            "askQty": 5500,
            "askPrice": 4.6,
            "underlyingValue": 133.9
        },
        "CE": {
            "strikePrice": 132,
            "expiryDate": "29-Feb-2024",
            "underlying": "TATASTEEL",
            "identifier": "OPTSTKTATASTEEL29-02-2024CE132.00",
            "openInterest": 43,
            "changeinOpenInterest": -4,
            "pchangeinOpenInterest": -8.51063829787234,
            "totalTradedVolume": 39,
            "impliedVolatility": 34.87,
            "lastPrice": 7.9,
            "change": -0.25,
            "pChange": -3.067484662576687,
            "totalBuyQuantity": 126500,
            "totalSellQuantity": 302500,
            "bidQty": 5500,
            "bidprice": 7.8,
            "askQty": 11000,
            "askPrice": 8,
            "underlyingValue": 133.9
        }
    },
    {
        "strikePrice": 133,
        "expiryDate": "29-Feb-2024",
        "PE": {
            "strikePrice": 133,
            "expiryDate": "29-Feb-2024",
            "underlying": "TATASTEEL",
            "identifier": "OPTSTKTATASTEEL29-02-2024PE133.00",
            "openInterest": 27,
            "changeinOpenInterest": 17,
            "pchangeinOpenInterest": 170,
            "totalTradedVolume": 22,
            "impliedVolatility": 32.23,
            "lastPrice": 4.55,
            "change": -0.5,
            "pChange": -9.900990099009901,
            "totalBuyQuantity": 231000,
            "totalSellQuantity": 247500,
            "bidQty": 11000,
            "bidprice": 4.85,
            "askQty": 5500,
            "askPrice": 5.1,
            "underlyingValue": 133.9
        },
        "CE": {
            "strikePrice": 133,
            "expiryDate": "29-Feb-2024",
            "underlying": "TATASTEEL",
            "identifier": "OPTSTKTATASTEEL29-02-2024CE133.00",
            "openInterest": 25,
            "changeinOpenInterest": 3,
            "pchangeinOpenInterest": 13.636363636363637,
            "totalTradedVolume": 38,
            "impliedVolatility": 34.55,
            "lastPrice": 7.3,
            "change": -0.10000000000000053,
            "pChange": -1.3513513513513586,
            "totalBuyQuantity": 121000,
            "totalSellQuantity": 126500,
            "bidQty": 5500,
            "bidprice": 7.1,
            "askQty": 5500,
            "askPrice": 7.35,
            "underlyingValue": 133.9
        }
    },
    {
        "strikePrice": 134,
        "expiryDate": "29-Feb-2024",
        "PE": {
            "strikePrice": 134,
            "expiryDate": "29-Feb-2024",
            "underlying": "TATASTEEL",
            "identifier": "OPTSTKTATASTEEL29-02-2024PE134.00",
            "openInterest": 28,
            "changeinOpenInterest": 13,
            "pchangeinOpenInterest": 86.66666666666667,
            "totalTradedVolume": 34,
            "impliedVolatility": 35.58,
            "lastPrice": 5.6,
            "change": 0.14999999999999947,
            "pChange": 2.7522935779816415,
            "totalBuyQuantity": 236500,
            "totalSellQuantity": 242000,
            "bidQty": 5500,
            "bidprice": 5.25,
            "askQty": 11000,
            "askPrice": 5.7,
            "underlyingValue": 133.9
        },
        "CE": {
            "strikePrice": 134,
            "expiryDate": "29-Feb-2024",
            "underlying": "TATASTEEL",
            "identifier": "OPTSTKTATASTEEL29-02-2024CE134.00",
            "openInterest": 39,
            "changeinOpenInterest": 12,
            "pchangeinOpenInterest": 44.44444444444444,
            "totalTradedVolume": 28,
            "impliedVolatility": 35.24,
            "lastPrice": 6.9,
            "change": -0.34999999999999964,
            "pChange": -4.827586206896547,
            "totalBuyQuantity": 319000,
            "totalSellQuantity": 264000,
            "bidQty": 5500,
            "bidprice": 6.8,
            "askQty": 11000,
            "askPrice": 6.9,
            "underlyingValue": 133.9
        }
    },
    {
        "strikePrice": 135,
        "expiryDate": "29-Feb-2024",
        "CE": {
            "strikePrice": 135,
            "expiryDate": "29-Feb-2024",
            "underlying": "TATASTEEL",
            "identifier": "OPTSTKTATASTEEL29-02-2024CE135.00",
            "openInterest": 996,
            "changeinOpenInterest": 98,
            "pchangeinOpenInterest": 10.913140311804009,
            "totalTradedVolume": 475,
            "impliedVolatility": 35.2,
            "lastPrice": 6.4,
            "change": -0.34999999999999964,
            "pChange": -5.18518518518518,
            "totalBuyQuantity": 649000,
            "totalSellQuantity": 825000,
            "bidQty": 5500,
            "bidprice": 6.35,
            "askQty": 5500,
            "askPrice": 6.45,
            "underlyingValue": 133.9
        },
        "PE": {
            "strikePrice": 135,
            "expiryDate": "29-Feb-2024",
            "underlying": "TATASTEEL",
            "identifier": "OPTSTKTATASTEEL29-02-2024PE135.00",
            "openInterest": 514,
            "changeinOpenInterest": 42,
            "pchangeinOpenInterest": 8.898305084745763,
            "totalTradedVolume": 179,
            "impliedVolatility": 35.89,
            "lastPrice": 6.15,
            "change": 0.10000000000000053,
            "pChange": 1.6528925619834798,
            "totalBuyQuantity": 533500,
            "totalSellQuantity": 561000,
            "bidQty": 5500,
            "bidprice": 5.95,
            "askQty": 5500,
            "askPrice": 6.15,
            "underlyingValue": 133.9
        }
    },
    {
        "strikePrice": 136,
        "expiryDate": "29-Feb-2024",
        "CE": {
            "strikePrice": 136,
            "expiryDate": "29-Feb-2024",
            "underlying": "TATASTEEL",
            "identifier": "OPTSTKTATASTEEL29-02-2024CE136.00",
            "openInterest": 57,
            "changeinOpenInterest": 7,
            "pchangeinOpenInterest": 14,
            "totalTradedVolume": 33,
            "impliedVolatility": 35.59,
            "lastPrice": 6,
            "change": -0.20000000000000018,
            "pChange": -3.2258064516129057,
            "totalBuyQuantity": 539000,
            "totalSellQuantity": 346500,
            "bidQty": 5500,
            "bidprice": 5.95,
            "askQty": 11000,
            "askPrice": 6.9,
            "underlyingValue": 133.9
        },
        "PE": {
            "strikePrice": 136,
            "expiryDate": "29-Feb-2024",
            "underlying": "TATASTEEL",
            "identifier": "OPTSTKTATASTEEL29-02-2024PE136.00",
            "openInterest": 9,
            "changeinOpenInterest": 6,
            "pchangeinOpenInterest": 200,
            "totalTradedVolume": 16,
            "impliedVolatility": 32.66,
            "lastPrice": 6.1,
            "change": -0.15000000000000036,
            "pChange": -2.4000000000000057,
            "totalBuyQuantity": 445500,
            "totalSellQuantity": 132000,
            "bidQty": 5500,
            "bidprice": 6.4,
            "askQty": 5500,
            "askPrice": 6.9,
            "underlyingValue": 133.9
        }
    },
    {
        "strikePrice": 137,
        "expiryDate": "29-Feb-2024",
        "CE": {
            "strikePrice": 137,
            "expiryDate": "29-Feb-2024",
            "underlying": "TATASTEEL",
            "identifier": "OPTSTKTATASTEEL29-02-2024CE137.00",
            "openInterest": 40,
            "changeinOpenInterest": 5,
            "pchangeinOpenInterest": 14.285714285714286,
            "totalTradedVolume": 25,
            "impliedVolatility": 36.4,
            "lastPrice": 5.7,
            "change": -0.14999999999999947,
            "pChange": -2.564102564102555,
            "totalBuyQuantity": 396000,
            "totalSellQuantity": 99000,
            "bidQty": 5500,
            "bidprice": 5.4,
            "askQty": 11000,
            "askPrice": 6.35,
            "underlyingValue": 133.9
        },
        "PE": {
            "strikePrice": 137,
            "expiryDate": "29-Feb-2024",
            "underlying": "TATASTEEL",
            "identifier": "OPTSTKTATASTEEL29-02-2024PE137.00",
            "openInterest": 5,
            "changeinOpenInterest": 4,
            "pchangeinOpenInterest": 400,
            "totalTradedVolume": 13,
            "impliedVolatility": 32.4,
            "lastPrice": 6.6,
            "change": -0.9000000000000004,
            "pChange": -12.000000000000005,
            "totalBuyQuantity": 115500,
            "totalSellQuantity": 88000,
            "bidQty": 5500,
            "bidprice": 6.85,
            "askQty": 11000,
            "askPrice": 7.5,
            "underlyingValue": 133.9
        }
    },
    {
        "strikePrice": 138,
        "expiryDate": "29-Feb-2024",
        "PE": {
            "strikePrice": 138,
            "expiryDate": "29-Feb-2024",
            "underlying": "TATASTEEL",
            "identifier": "OPTSTKTATASTEEL29-02-2024PE138.00",
            "openInterest": 16,
            "changeinOpenInterest": 15,
            "pchangeinOpenInterest": 1500,
            "totalTradedVolume": 21,
            "impliedVolatility": 36.82,
            "lastPrice": 7.95,
            "change": -0.9999999999999991,
            "pChange": -11.17318435754189,
            "totalBuyQuantity": 110000,
            "totalSellQuantity": 275000,
            "bidQty": 5500,
            "bidprice": 7.6,
            "askQty": 5500,
            "askPrice": 9,
            "underlyingValue": 133.9
        },
        "CE": {
            "strikePrice": 138,
            "expiryDate": "29-Feb-2024",
            "underlying": "TATASTEEL",
            "identifier": "OPTSTKTATASTEEL29-02-2024CE138.00",
            "openInterest": 113,
            "changeinOpenInterest": 32,
            "pchangeinOpenInterest": 39.50617283950617,
            "totalTradedVolume": 56,
            "impliedVolatility": 35.95,
            "lastPrice": 5.2,
            "change": -0.34999999999999964,
            "pChange": -6.3063063063063005,
            "totalBuyQuantity": 489500,
            "totalSellQuantity": 165000,
            "bidQty": 5500,
            "bidprice": 5.2,
            "askQty": 5500,
            "askPrice": 5.3,
            "underlyingValue": 133.9
        }
    },
    {
        "strikePrice": 139,
        "expiryDate": "29-Feb-2024",
        "PE": {
            "strikePrice": 139,
            "expiryDate": "29-Feb-2024",
            "underlying": "TATASTEEL",
            "identifier": "OPTSTKTATASTEEL29-02-2024PE139.00",
            "openInterest": 9,
            "changeinOpenInterest": 1,
            "pchangeinOpenInterest": 12.5,
            "totalTradedVolume": 4,
            "impliedVolatility": 33.72,
            "lastPrice": 8,
            "change": -0.4499999999999993,
            "pChange": -5.32544378698224,
            "totalBuyQuantity": 77000,
            "totalSellQuantity": 225500,
            "bidQty": 22000,
            "bidprice": 7.7,
            "askQty": 5500,
            "askPrice": 10.6,
            "underlyingValue": 133.9
        },
        "CE": {
            "strikePrice": 139,
            "expiryDate": "29-Feb-2024",
            "underlying": "TATASTEEL",
            "identifier": "OPTSTKTATASTEEL29-02-2024CE139.00",
            "openInterest": 16,
            "changeinOpenInterest": 15,
            "pchangeinOpenInterest": 1500,
            "totalTradedVolume": 25,
            "impliedVolatility": 36.5,
            "lastPrice": 4.9,
            "change": -0.4499999999999993,
            "pChange": -8.411214953271015,
            "totalBuyQuantity": 396000,
            "totalSellQuantity": 60500,
            "bidQty": 5500,
            "bidprice": 4.3,
            "askQty": 5500,
            "askPrice": 5.7,
            "underlyingValue": 133.9
        }
    },
    {
        "strikePrice": 140,
        "expiryDate": "29-Feb-2024",
        "CE": {
            "strikePrice": 140,
            "expiryDate": "29-Feb-2024",
            "underlying": "TATASTEEL",
            "identifier": "OPTSTKTATASTEEL29-02-2024CE140.00",
            "openInterest": 3164,
            "changeinOpenInterest": 364,
            "pchangeinOpenInterest": 13,
            "totalTradedVolume": 1241,
            "impliedVolatility": 37.22,
            "lastPrice": 4.65,
            "change": -0.2999999999999998,
            "pChange": -6.060606060606057,
            "totalBuyQuantity": 1138500,
            "totalSellQuantity": 2392500,
            "bidQty": 55000,
            "bidprice": 4.6,
            "askQty": 22000,
            "askPrice": 4.7,
            "underlyingValue": 133.9
        },
        "PE": {
            "strikePrice": 140,
            "expiryDate": "29-Feb-2024",
            "underlying": "TATASTEEL",
            "identifier": "OPTSTKTATASTEEL29-02-2024PE140.00",
            "openInterest": 850,
            "changeinOpenInterest": 1,
            "pchangeinOpenInterest": 0.11778563015312132,
            "totalTradedVolume": 145,
            "impliedVolatility": 37.95,
            "lastPrice": 9.35,
            "change": 0.15000000000000036,
            "pChange": 1.6304347826086998,
            "totalBuyQuantity": 198000,
            "totalSellQuantity": 330000,
            "bidQty": 5500,
            "bidprice": 9.35,
            "askQty": 11000,
            "askPrice": 9.55,
            "underlyingValue": 133.9
        }
    },
    {
        "strikePrice": 141,
        "expiryDate": "29-Feb-2024",
        "CE": {
            "strikePrice": 141,
            "expiryDate": "29-Feb-2024",
            "underlying": "TATASTEEL",
            "identifier": "OPTSTKTATASTEEL29-02-2024CE141.00",
            "openInterest": 75,
            "changeinOpenInterest": 22,
            "pchangeinOpenInterest": 41.509433962264154,
            "totalTradedVolume": 43,
            "impliedVolatility": 37.54,
            "lastPrice": 4.35,
            "change": -0.20000000000000018,
            "pChange": -4.3956043956043995,
            "totalBuyQuantity": 467500,
            "totalSellQuantity": 258500,
            "bidQty": 5500,
            "bidprice": 3.9,
            "askQty": 5500,
            "askPrice": 4.75,
            "underlyingValue": 133.9
        },
        "PE": {
            "strikePrice": 141,
            "expiryDate": "29-Feb-2024",
            "underlying": "TATASTEEL",
            "identifier": "OPTSTKTATASTEEL29-02-2024PE141.00",
            "openInterest": 10,
            "changeinOpenInterest": 10,
            "pchangeinOpenInterest": 0,
            "totalTradedVolume": 16,
            "impliedVolatility": 37.17,
            "lastPrice": 9.85,
            "change": -5.300000000000001,
            "pChange": -34.98349834983499,
            "totalBuyQuantity": 99000,
            "totalSellQuantity": 99000,
            "bidQty": 5500,
            "bidprice": 9.35,
            "askQty": 11000,
            "askPrice": 10.5,
            "underlyingValue": 133.9
        }
    },
    {
        "strikePrice": 142,
        "expiryDate": "29-Feb-2024",
        "PE": {
            "strikePrice": 142,
            "expiryDate": "29-Feb-2024",
            "underlying": "TATASTEEL",
            "identifier": "OPTSTKTATASTEEL29-02-2024PE142.00",
            "openInterest": 5,
            "changeinOpenInterest": 5,
            "pchangeinOpenInterest": 0,
            "totalTradedVolume": 18,
            "impliedVolatility": 37.13,
            "lastPrice": 10.5,
            "change": -5.35,
            "pChange": -33.753943217665615,
            "totalBuyQuantity": 264000,
            "totalSellQuantity": 253000,
            "bidQty": 5500,
            "bidprice": 10.2,
            "askQty": 5500,
            "askPrice": 11.35,
            "underlyingValue": 133.9
        },
        "CE": {
            "strikePrice": 142,
            "expiryDate": "29-Feb-2024",
            "underlying": "TATASTEEL",
            "identifier": "OPTSTKTATASTEEL29-02-2024CE142.00",
            "openInterest": 73,
            "changeinOpenInterest": 34,
            "pchangeinOpenInterest": 87.17948717948718,
            "totalTradedVolume": 46,
            "impliedVolatility": 37.45,
            "lastPrice": 4,
            "change": -0.15000000000000036,
            "pChange": -3.6144578313253093,
            "totalBuyQuantity": 308000,
            "totalSellQuantity": 148500,
            "bidQty": 5500,
            "bidprice": 3.7,
            "askQty": 5500,
            "askPrice": 4.05,
            "underlyingValue": 133.9
        }
    },
    {
        "strikePrice": 143,
        "expiryDate": "29-Feb-2024",
        "CE": {
            "strikePrice": 143,
            "expiryDate": "29-Feb-2024",
            "underlying": "TATASTEEL",
            "identifier": "OPTSTKTATASTEEL29-02-2024CE143.00",
            "openInterest": 0,
            "changeinOpenInterest": 0,
            "pchangeinOpenInterest": 0,
            "totalTradedVolume": 0,
            "impliedVolatility": 0,
            "lastPrice": 0,
            "change": 0,
            "pChange": 0,
            "totalBuyQuantity": 341000,
            "totalSellQuantity": 0,
            "bidQty": 165000,
            "bidprice": 1.6,
            "askQty": 0,
            "askPrice": 0,
            "underlyingValue": 133.9
        },
        "PE": {
            "strikePrice": 143,
            "expiryDate": "29-Feb-2024",
            "underlying": "TATASTEEL",
            "identifier": "OPTSTKTATASTEEL29-02-2024PE143.00",
            "openInterest": 0,
            "changeinOpenInterest": 0,
            "pchangeinOpenInterest": 0,
            "totalTradedVolume": 0,
            "impliedVolatility": 0,
            "lastPrice": 0,
            "change": 0,
            "pChange": 0,
            "totalBuyQuantity": 225500,
            "totalSellQuantity": 187000,
            "bidQty": 5500,
            "bidprice": 10.05,
            "askQty": 5500,
            "askPrice": 13.55,
            "underlyingValue": 133.9
        }
    }
]